redicts/__init__.py
redicts/_compat.py
redicts/errors.py
redicts/lock.py
redicts/proxy.py
redicts/util.py
redicts-1.0.6.dist-info/DESCRIPTION.rst
redicts-1.0.6.dist-info/METADATA
redicts-1.0.6.dist-info/RECORD
redicts-1.0.6.dist-info/WHEEL
redicts-1.0.6.dist-info/metadata.json
redicts-1.0.6.dist-info/top_level.txt
