Metadata-Version: 2.0
Name: redicts
Version: 1.0.6
Summary: Save arbitary nested python dicts and objects in redis
Home-page: http://github.com/adnymics/redicts
Author: adnymics
Author-email: dev@adnymics.com
License: GPLv3
Platform: UNKNOWN
Classifier: Development Status :: 4 - Beta
Classifier: Topic :: Database
Classifier: Topic :: Software Development :: Libraries :: Python Modules
